interactive_dir_utils/__init__.py
interactive_dir_utils/data_dir_utils.py
interactive_dir_utils-0.1.2.dist-info/License.txt
interactive_dir_utils-0.1.2.dist-info/METADATA
interactive_dir_utils-0.1.2.dist-info/WHEEL
interactive_dir_utils-0.1.2.dist-info/RECORD
